iop/__init__.py
iop/core/__init__.py
iop/core/message.py
iop/core/util.py
iop/input/__init__.py
iop/input/mail.py
iop/input/scheduler.py
iop/ipc/__init__.py
iop/ipc/input.py
iop/ipc/output.py
iop/output/__init__.py
iop/process/__init__.py
iop/process/render.py
iop/runner/__init__.py
iop/runner/main.py
iop-0.0.4.dist-info/DESCRIPTION.rst
iop-0.0.4.dist-info/METADATA
iop-0.0.4.dist-info/RECORD
iop-0.0.4.dist-info/WHEEL
iop-0.0.4.dist-info/entry_points.txt
iop-0.0.4.dist-info/metadata.json
iop-0.0.4.dist-info/top_level.txt
